eagerx_franka/__init__.py
eagerx_franka/assets/calibrations/logitech_c170.yaml
eagerx_franka/assets/calibrations/logitech_c920.yaml
eagerx_franka/assets/franka_description.launch
eagerx_franka/assets/franka_panda/LICENSE.txt
eagerx_franka/assets/franka_panda/meshes/collision/finger.obj
eagerx_franka/assets/franka_panda/meshes/collision/hand.obj
eagerx_franka/assets/franka_panda/meshes/collision/link0.obj
eagerx_franka/assets/franka_panda/meshes/collision/link1.obj
eagerx_franka/assets/franka_panda/meshes/collision/link2.obj
eagerx_franka/assets/franka_panda/meshes/collision/link3.obj
eagerx_franka/assets/franka_panda/meshes/collision/link4.obj
eagerx_franka/assets/franka_panda/meshes/collision/link5.obj
eagerx_franka/assets/franka_panda/meshes/collision/link6.mtl
eagerx_franka/assets/franka_panda/meshes/collision/link6.obj
eagerx_franka/assets/franka_panda/meshes/collision/link7.obj
eagerx_franka/assets/franka_panda/meshes/visual/colors.png
eagerx_franka/assets/franka_panda/meshes/visual/finger.mtl
eagerx_franka/assets/franka_panda/meshes/visual/finger.obj
eagerx_franka/assets/franka_panda/meshes/visual/hand.mtl
eagerx_franka/assets/franka_panda/meshes/visual/hand.obj
eagerx_franka/assets/franka_panda/meshes/visual/link1.mtl
eagerx_franka/assets/franka_panda/meshes/visual/link1.obj
eagerx_franka/assets/franka_panda/meshes/visual/link2.mtl
eagerx_franka/assets/franka_panda/meshes/visual/link2.obj
eagerx_franka/assets/franka_panda/meshes/visual/link3.mtl
eagerx_franka/assets/franka_panda/meshes/visual/link3.obj
eagerx_franka/assets/franka_panda/meshes/visual/link4.mtl
eagerx_franka/assets/franka_panda/meshes/visual/link4.obj
eagerx_franka/assets/franka_panda/meshes/visual/link5.mtl
eagerx_franka/assets/franka_panda/meshes/visual/link5.obj
eagerx_franka/assets/franka_panda/meshes/visual/link6.mtl
eagerx_franka/assets/franka_panda/meshes/visual/link6.obj
eagerx_franka/assets/franka_panda/meshes/visual/visualShapeBench.json_0.json
eagerx_franka-0.0.12.dist-info/LICENSE
eagerx_franka-0.0.12.dist-info/METADATA
eagerx_franka-0.0.12.dist-info/WHEEL
eagerx_franka-0.0.12.dist-info/RECORD
